setup.py
neatek_python_chat_server.egg-info/PKG-INFO
neatek_python_chat_server.egg-info/SOURCES.txt
neatek_python_chat_server.egg-info/dependency_links.txt
neatek_python_chat_server.egg-info/top_level.txt
server/__init__.py
server/launcher.py
server/server.py
server/common/__init__.py
server/common/decos.py
server/common/descryptors.py
server/common/errors.py
server/common/metaclasses.py
server/common/utils.py
server/common/variables.py
server/logs/__init__.py
server/logs/config_client_log.py
server/logs/config_server_log.py
server/server/__init__.py
server/server/config_window.py
server/server/main_window.py
server/server/server_add_user.py
server/server/server_database.py
server/server/server_main.py
server/server/server_remove_user.py
server/server/stat_window.py
server/unit_tests/__init__.py