Metadata-Version: 2.1
Name: neatek-python-chat-server
Version: 0.1
Summary: Server packet
Author: Vladimir Zhelnov
Author-email: neatek@icloud.com
